{
  "version": "1.0",
  "plugins": {
    "java-client-codegen": {
      "service": "com.example#CoffeeShop",
      // TODO: Make plugin aware of existing?
      "namespace": "software.amazon.smithy.java.client.example",
      "headerFile": "license.txt",
      "protocol": "aws.protocols#restJson1",
      "transport": {
        "http-java": {}
      }
    },
    "java-server-codegen": {
      "service": "com.example#CoffeeShop",
      "namespace": "software.amazon.smithy.java.server.example",
      "headerFile": "license.txt"
    }
  }
}
